heapsy/__init__.py
heapsy-0.0.2.dist-info/LICENSE
heapsy-0.0.2.dist-info/METADATA
heapsy-0.0.2.dist-info/WHEEL
heapsy-0.0.2.dist-info/top_level.txt
heapsy-0.0.2.dist-info/RECORD
