Metadata-Version: 2.1
Name: heapsy
Version: 0.0.2
Summary: Python heap usage inspector
Home-page: https://github.com/ashon/heapsy
Author: ashon lee
Author-email: ashon8813@gmail.com
License: MIT
Platform: UNKNOWN
Classifier: Programming Language :: Python :: 3
Classifier: License :: OSI Approved :: MIT License
Classifier: Operating System :: OS Independent
Requires-Python: >=3
